[{"info":"M 18 x 2 - 7H","diam":"18","pitch":"2","tolerance":"7H","depth":1.082531755,"type_pitch":2.0,"range_main":2.0,"range_sub":null,"isMale":false,"d_ei":0.0,"d2_es":0.265,"d2_ei":0.0,"d1_es":0.475,"d1_ei":0.0,"pitch_diam_d2":16.700961894,"minor_diam_d1":15.83493649,"minor_diam_d3":15.546261356,"h":1.732050808,"h_5_8":1.082531754,"h_3_8":0.649519052,"h_4":0.433012702,"h_8":0.21650635,"minor_diam_max":16.30993649,"minor_diam_min":15.83493649,"minor_diam_medium":16.07243649,"mean_diam_max":16.965961894,"mean_diam_min":16.700961894,"mean_diam_medium":16.833461894}]