[{"info":"M 7.5 x 0.75 - 6H","diam":"7.5","pitch":"0.75","tolerance":"6H","depth":0.4059494081,"type_pitch":3.0,"range_main":null,"range_sub":2.0,"isMale":false,"d_ei":0.0,"d2_es":0.132,"d2_ei":0.0,"d1_es":0.19,"d1_ei":0.0,"pitch_diam_d2":7.0128607103,"minor_diam_d1":6.6881011837,"minor_diam_d3":6.5798480085,"h":0.649519053,"h_5_8":0.4059494078,"h_3_8":0.2435696445,"h_4":0.1623797633,"h_8":0.0811898812,"minor_diam_max":6.8781011838,"minor_diam_min":6.6881011837,"minor_diam_medium":6.7831011838,"mean_diam_max":7.1448607102,"mean_diam_min":7.0128607103,"mean_diam_medium":7.0788607102}]