[{"info":"M 1.4 x 0.3 - 5h4h","diam":1.4,"pitch":0.3,"tolerance":"5h4h","isMale":true,"depth":0.1840303983,"type_pitch":1.0,"range_main":2.0,"range_sub":null,"major_diam_max":1.4,"major_diam_mean":1.376,"major_diam_min":1.352,"pitch_diam_max":1.2051442841,"pitch_diam_mean":1.1826442841,"pitch_diam_min":1.1601442841,"pitch_diam_d2":1.2051442841,"minor_diam_d1":1.0752404735,"minor_diam_d3":1.0319392034,"d_es":0.0,"d_ei":-0.048,"d2_es":0.0,"d2_ei":-0.045,"d1_es":0.0,"h":0.2598076212,"h_5_8":0.1623797631,"h_3_8":0.0974278578,"h_4":0.0649519053,"h_8":0.0324759525}]