[{"info":"M 540 x 6 - 7e6e","diam":540.0,"pitch":6.0,"tolerance":"7e6e","isMale":true,"depth":3.680607966,"type_pitch":2.0,"range_main":2.0,"range_sub":null,"major_diam_max":539.882,"major_diam_mean":539.582,"major_diam_min":539.282,"pitch_diam_max":535.984885682,"pitch_diam_mean":535.772385682,"pitch_diam_min":535.559885682,"pitch_diam_d2":536.102885682,"minor_diam_d1":533.50480947,"minor_diam_d3":532.638784068,"d_es":-0.118,"d_ei":-0.718,"d2_es":-0.118,"d2_ei":-0.543,"d1_es":-0.118,"h":5.196152424,"h_5_8":3.247595262,"h_3_8":1.948557156,"h_4":1.299038106,"h_8":0.64951905}]